README.md
easy_sqla/.DS_Store
easy_sqla/__init__.py
easy_sqla/context.py
easy_sqla/db/__init__.py
easy_sqla/db/operators.py
easy_sqla/db/query.py
easy_sqla/db/selector.py
easy_sqla/db/settings.py
easy_sqla/exceptions.py
easy_sqla/logger.py
easy_sqla/manager.py
easy_sqla/utils.py
tests/.coveragerc
tests/__init__.py
tests/base_model.py
tests/conftest.py
tests/db/__init__.py
tests/db/test_operators.py
tests/db/test_query.py
tests/db/test_settings.py
tests/models.py
tests/test_context.py
tests/test_manager.py
tests/test_utils.py
easy_sqla_lib-2.0.0.dist-info/METADATA
easy_sqla_lib-2.0.0.dist-info/WHEEL
easy_sqla_lib-2.0.0.dist-info/RECORD
