Metadata-Version: 2.1
Name: easy-sqla-lib
Version: 2.0.0
Summary: A wrapper on top of sqlalchemy that allow to make django orm style query
License: GNU GPLv3
Author: Soumaila Kouriba
Author-email: admin@softmali.com
Requires-Python: >=3.9,<4.0
Classifier: License :: Other/Proprietary License
Classifier: Programming Language :: Python :: 3
Classifier: Programming Language :: Python :: 3.9
Classifier: Programming Language :: Python :: 3.10
Classifier: Programming Language :: Python :: 3.11
Classifier: Programming Language :: Python :: 3.12
Requires-Dist: PyYAML (>=6.0,<7.0)
Requires-Dist: SQLAlchemy (>=2,<3)
Requires-Dist: psycopg2-binary (>=2.9.6,<3.0.0)
Requires-Dist: pydantic (>=2.7.0,<3.0.0)
Requires-Dist: toml (>=0.10.2,<0.11.0)
